spicy_snow/__init__.py
spicy_snow/find_data.py
spicy_snow/hyp3_pipeline.py
spicy_snow/retrieval.py
spicy_snow/spicy_constants.py
spicy_snow/processing/__init__.py
spicy_snow/processing/generate_dataarrays.py
spicy_snow/processing/s1_preprocessing.py
spicy_snow/processing/snow_index.py
spicy_snow/processing/wet_snow.py
spicy_snow/utils/__init__.py
spicy_snow/utils/checks.py
spicy_snow/utils/download.py
spicy_snow/utils/geometry.py
spicy_snow/utils/nsidc.py
spicy_snow/utils/raster.py
spicy_snow/utils/spicy_logging.py
spicy_snow-0.3.8.dist-info/licenses/LICENSE
spicy_snow-0.3.8.dist-info/METADATA
spicy_snow-0.3.8.dist-info/WHEEL
spicy_snow-0.3.8.dist-info/top_level.txt
spicy_snow-0.3.8.dist-info/RECORD
