Metadata-Version: 2.4
Name: spicy-snow
Version: 0.3.8
Summary: Snow Depth Retrievals from Sentinel-1 Backscatter.
Home-page: https://github.com/SnowEx/spicy-snow
Author: Zach Hoppinen
Author-email: zachhoppinen@gmail.com
License: MIT
Classifier: Programming Language :: Python :: 3
Classifier: Programming Language :: Python :: 3.9
Classifier: Programming Language :: Python :: 3.10
Classifier: Programming Language :: Python :: 3.11
Classifier: Programming Language :: Python :: Implementation :: CPython
Requires-Python: >=3.9,<=3.12
License-File: LICENSE
Requires-Dist: numpy
Requires-Dist: pandas
Requires-Dist: xarray
Requires-Dist: geopandas
Requires-Dist: rioxarray
Requires-Dist: shapely
Requires-Dist: asf_search
Requires-Dist: hyp3_sdk
Requires-Dist: earthaccess
Requires-Dist: matplotlib
Requires-Dist: netcdf4
Requires-Dist: h5py
Requires-Dist: pygeohydro
Requires-Dist: zarr
Requires-Dist: dask
Dynamic: author
Dynamic: author-email
Dynamic: classifier
Dynamic: description
Dynamic: description-content-type
Dynamic: home-page
Dynamic: license
Dynamic: license-file
Dynamic: requires-dist
Dynamic: requires-python
Dynamic: summary
